<starmap id="pahang" img="data/Pahang.png" displayName="Pahang">
  <item id="P78" displayName="Cameron Highlands">
    <shape type="poly" coords="267,127, 251,149, 254,158, 249,162, 247,184, 240,190, 248,205, 248,221, 250,230, 265,227, 277,231, 279,235, 278,242, 279,251, 272,263, 280,271, 267,302, 258,312, 249,314, 245,326, 242,327, 235,323, 230,307, 219,304, 212,295, 205,296, 204,304, 199,305, 193,311, 181,308, 169,303, 166,308, 155,308, 151,304, 136,293, 128,293, 125,280, 125,273, 130,265, 112,261, 109,255, 114,248, 105,240, 107,224, 104,221, 101,219, 104,205, 104,200, 95,200, 90,195, 81,196, 74,192, 74,189, 68,185, 78,172, 78,167, 81,166, 86,160, 83,153, 77,149, 75,133, 83,127, 95,125, 107,137, 118,136, 119,131, 126,127, 132,127, 142,137, 151,139, 155,145, 164,144, 166,147, 174,142, 181,144, 188,132, 198,130, 204,124, 210,129, 214,123, 216,121, 220,106, 221,106, 219,95, 222,93, 222,90, 221,81, 222,75, 232,76, 235,79, 235,88, 242,88, 243,99, 250,99, 259,106, 263,128, "/>
  </item>
  <item id="P79" displayName="Lipis">
    <shape type="poly" coords="373,122, 373,133, 385,156, 379,173, 383,186, 371,196, 371,220, 378,231, 377,245, 388,262, 381,294, 401,301, 401,310, 387,317, 370,327, 352,321, 348,314, 332,308, 328,323, 336,332, 339,332, 332,345, 314,345, 307,339, 302,345, 298,354, 287,361, 278,357, 277,349, 285,336, 280,322, 282,308, 278,307, 272,301, 269,303, 282,270, 275,264, 281,251, 280,242, 283,236, 280,230, 265,224, 252,227, 250,221, 250,204, 244,191, 248,184, 251,162, 257,158, 253,150, 269,126, 269,121, 274,113, 276,112, 282,91, 282,76, 285,74, 293,80, 296,77, 297,75, 304,83, 307,83, 309,82, 316,88, 317,81, 324,81, 330,75, 336,74, 341,81, 341,92, 350,97, 356,102, 356,109, "/>
  </item>
  <item id="P80" displayName="Raub">
    <shape type="poly" coords="320,348, 323,362, 329,371, 324,390, 333,395, 331,398, 326,421, 316,437, 312,441, 314,463, 308,467, 309,473, 304,487, 291,487, 283,478, 281,460, 274,453, 264,451, 253,444, 250,447, 257,455, 250,462, 244,461, 236,465, 236,468, 230,469, 220,453, 220,447, 212,444, 207,439, 194,437, 176,427, 171,420, 169,412, 160,407, 160,401, 158,394, 162,389, 162,381, 150,366, 153,360, 149,334, 147,333, 147,325, 153,311, 167,310, 171,305, 182,310, 194,313, 199,307, 207,306, 209,298, 213,299, 219,308, 229,308, 235,326, 243,330, 247,328, 251,318, 257,314, 267,305, 272,303, 277,309, 281,312, 278,321, 284,337, 274,349, 277,359, 288,364, 300,357, 303,346, 309,342, 313,348, "/>
  </item>
  <item id="P81" displayName="Jerantut">
    <shape type="poly" coords="335,392, 348,387, 364,386, 370,391, 376,383, 376,376, 382,382, 384,395, 397,390, 405,402, 407,398, 424,402, 436,421, 449,426, 455,434, 468,410, 479,403, 482,405, 496,401, 493,393, 502,390, 511,397, 522,388, 527,392, 541,392, 547,385, 547,382, 554,375, 554,369, 560,365, 570,355, 573,347, 587,358, 594,351, 594,344, 598,335, 612,329, 616,301, 605,292, 609,285, 613,284, 615,270, 614,265, 619,255, 619,241, 625,236, 630,228, 636,217, 647,223, 647,217, 646,205, 653,200, 650,196, 647,196, 645,182, 642,180, 633,173, 626,175, 628,180, 621,180, 617,174, 613,176, 605,175, 602,176, 597,167, 589,166, 584,147, 589,145, 596,143, 600,137, 597,129, 600,128, 598,113, 587,102, 566,102, 556,99, 550,100, 542,91, 533,87, 526,75, 525,72, 520,72, 509,68, 507,70, 509,79, 506,82, 507,88, 507,97, 501,95, 494,97, 489,92, 479,102, 470,104, 458,96, 454,91, 450,90, 441,92, 439,89, 433,90, 425,90, 422,93, 428,99, 425,104, 421,106, 416,114, 406,114, 391,110, 379,110, 379,116, 376,120, 376,130, 387,156, 381,173, 385,186, 374,196, 374,219, 379,228, 379,238, 390,261, 385,294, 405,300, 402,312, 389,318, 377,326, 370,330, 351,323, 347,314, 334,310, 330,323, 337,330, 342,330, 334,346, 322,347, 325,361, 332,370, 325,389, "/>
  </item>
  <item id="P82" displayName="Indera Mahkota">
    <shape type="poly" coords="745,368, 736,376, 731,382, 738,402, 747,404, 761,394, 772,394, 770,364, 774,356, 785,348, 789,349, 792,348, 780,319, 779,294, 787,283, 788,277, 792,276, 761,275, 756,271, 759,292, 752,297, 749,310, 756,319, 757,340, 760,354, 757,361, 752,364, 756,373, 752,381, "/>
  </item>
  <item id="P83" displayName="Kuantan">
    <shape type="poly" coords="737,404, 736,416, 733,419, 760,473, 775,475, 781,472, 757,432, 758,411, 762,403, 771,400, 772,397, 763,396, 748,407, "/>
  </item>
  <item id="P84" displayName="Paya Besar">
    <shape type="poly" coords="732,416, 714,417, 712,423, 704,430, 699,442, 694,444, 686,443, 677,448, 683,466, 616,456, 602,438, 593,434, 585,438, 583,434, 576,429, 575,419, 559,420, 553,410, 545,401, 543,394, 549,387, 549,384, 555,375, 555,370, 560,368, 564,363, 572,357, 575,350, 589,361, 597,353, 597,343, 600,336, 615,332, 616,321, 616,317, 618,302, 641,292, 648,291, 651,296, 669,300, 669,305, 685,312, 689,319, 694,319, 702,326, 708,326, 712,322, 715,329, 719,334, 723,331, 726,331, 726,336, 733,342, 738,348, 735,354, 744,367, 736,372, 729,382, 730,390, 736,404, 736,412, "/>
  </item>
  <item id="P85" displayName="Pekan">
    <shape type="poly" coords="617,458, 618,480, 594,517, 591,517, 585,524, 574,521, 569,526, 569,533, 584,552, 584,555, 589,569, 610,588, 614,589, 620,575, 627,575, 633,581, 639,585, 663,571, 672,575, 671,589, 688,611, 687,615, 688,625, 729,639, 728,676, 722,685, 722,688, 722,694, 726,696, 775,696, 792,701, 795,664, 798,647, 789,554, 799,521, 805,517, 807,511, 804,509, 799,511, 777,511, 777,507, 790,505, 798,502, 800,496, 782,475, 777,477, 771,476, 760,474, 732,418, 714,419, 714,423, 707,430, 701,445, 694,448, 687,444, 680,451, 685,468, "/>
  </item>
  <item id="P86" displayName="Maran">
    <shape type="poly" coords="495,405, 497,408, 501,434, 507,439, 509,458, 509,475, 501,484, 495,482, 490,489, 471,485, 471,493, 468,501, 474,521, 500,529, 505,536, 505,542, 506,545, 513,545, 519,542, 527,538, 529,550, 531,559, 539,557, 544,561, 543,567, 539,570, 539,573, 542,574, 546,571, 551,553, 555,552, 564,554, 582,552, 567,535, 566,525, 574,519, 582,522, 590,514, 594,515, 603,500, 614,480, 614,457, 602,440, 594,435, 590,437, 583,440, 581,436, 575,431, 573,421, 557,423, 554,416, 552,410, 543,403, 541,395, 529,394, 523,391, 511,399, 504,394, 497,394, 498,401, "/>
  </item>
  <item id="P87" displayName="Kuala Krau">
    <shape type="poly" coords="466,498, 452,497, 449,491, 443,489, 436,493, 436,496, 412,498, 410,499, 404,499, 387,474, 386,470, 388,463, 385,459, 379,462, 376,460, 363,462, 355,457, 345,449, 340,447, 337,446, 333,426, 328,421, 333,398, 337,393, 351,388, 365,387, 371,393, 378,384, 378,379, 380,382, 383,398, 397,392, 406,404, 408,401, 423,402, 435,422, 449,429, 456,436, 467,418, 471,410, 481,404, 483,407, 491,404, 494,407, 498,435, 505,439, 507,457, 506,471, 500,481, 495,480, 491,484, 469,481, 470,491, "/>
  </item>
  <item id="P88" displayName="Temerloh">
    <shape type="poly" coords="306,487, 317,497, 321,508, 334,517, 335,546, 341,560, 349,560, 369,555, 374,548, 384,546, 388,553, 407,559, 411,552, 420,553, 425,548, 431,554, 442,556, 452,551, 457,556, 460,554, 465,540, 470,536, 472,522, 466,510, 465,503, 450,500, 446,494, 444,493, 438,498, 438,501, 415,499, 412,504, 407,503, 403,502, 385,478, 383,472, 386,465, 384,461, 382,466, 373,462, 363,465, 355,459, 344,451, 339,450, 335,446, 333,428, 329,426, 320,434, 315,441, 317,461, 312,465, 310,477, "/>
  </item>
  <item id="P89" displayName="Bentong">
    <shape type="poly" coords="408,561, 413,572, 407,579, 403,576, 403,585, 399,589, 398,608, 392,614, 403,626, 398,635, 354,621, 349,615, 342,615, 340,612, 327,617, 322,625, 316,621, 312,606, 309,603, 302,603, 290,597, 289,588, 280,586, 275,582, 271,591, 258,591, 225,568, 222,559, 217,553, 217,545, 225,534, 217,512, 224,495, 231,492, 233,477, 233,471, 238,469, 239,466, 244,462, 250,464, 259,456, 253,446, 253,444, 263,452, 275,456, 280,461, 282,480, 290,488, 297,489, 305,489, 315,497, 320,509, 328,514, 333,517, 334,547, 340,561, 347,561, 354,559, 372,555, 376,550, 382,549, 386,555, "/>
  </item>
  <item id="P90" displayName="Bera">
    <shape type="poly" coords="540,575, 540,577, 543,591, 557,611, 571,616, 576,625, 560,632, 557,630, 551,633, 548,644, 555,641, 560,662, 569,669, 560,691, 560,717, 558,735, 570,751, 541,741, 537,724, 532,720, 530,723, 462,678, 435,644, 399,636, 403,630, 406,626, 394,615, 399,607, 401,591, 404,587, 404,580, 407,582, 415,573, 410,560, 411,555, 421,555, 425,550, 429,556, 443,557, 452,553, 457,558, 462,556, 466,542, 473,539, 476,524, 498,529, 503,535, 502,543, 506,547, 513,548, 520,544, 528,541, 526,552, 530,561, 535,561, 540,559, 541,564, 536,570, 537,575, "/>
  </item>
  <item id="P91" displayName="Rompin">
    <shape type="poly" coords="792,705, 775,699, 723,699, 718,693, 721,689, 720,683, 726,676, 727,640, 684,626, 685,620, 684,615, 687,609, 668,588, 668,577, 667,574, 640,588, 631,582, 628,577, 622,578, 615,592, 608,591, 587,569, 583,559, 583,555, 566,557, 556,554, 554,555, 549,573, 542,577, 544,589, 558,609, 572,614, 579,625, 561,634, 557,632, 552,634, 549,640, 556,639, 561,660, 572,668, 566,683, 561,692, 562,716, 561,721, 559,734, 632,822, 695,848, 766,826, 788,836, 800,839, 808,847, 854,869, 856,865, 859,868, 862,862, 862,857, 855,850, 858,846, 849,846, 848,837, 855,834, 855,830, 851,830, 856,825, 859,825, 857,806, 852,809, 848,803, 861,798, 827,766, 815,752, 808,752, 802,746, 806,741, 795,718, "/>
    <shape type="poly" coords="920,686, 917,688, 919,694, 923,697, 921,700, 921,713, 900,714, 890,704, 889,687, 902,680, 903,676, 899,663, 901,658, 900,654, 903,653, 910,660, "/>
    <shape type="poly" coords="909,794, 913,799, 909,799, "/>
    <shape type="poly" coords="932,787, 935,789, 932,792, 931,789, "/>
    <shape type="poly" coords="938,786, 938,792, 943,795, 943,788, "/>
  </item>
</starmap>